prestool/PresMongo.py
prestool/PresMySql.py
prestool/PresRedis.py
prestool/PresSqlite.py
prestool/Tool.py
prestool/Utils.py
prestool/__init__.py
prestool-1.0.2.dist-info/METADATA
prestool-1.0.2.dist-info/WHEEL
prestool-1.0.2.dist-info/licenses/LICENSE
prestool-1.0.2.dist-info/RECORD
