Metadata-Version: 2.4
Name: prestool
Version: 1.0.2
Summary: 包含了多种常用的python相关工具以及sql生成等
Project-URL: Homepage, https://gitee.com/prestest/pres-pip-prestool
Project-URL: Bug Tracker, https://gitee.com/prestest/pres-pip-prestool/issues
Author-email: preszang <preszang@foxmail.com>
Maintainer-email: preszang <preszang@foxmail.com>
License: Copyright <2020> <COPYRIGHT preszang>
License-File: LICENSE
Classifier: License :: OSI Approved :: MIT License
Classifier: Operating System :: OS Independent
Classifier: Programming Language :: Python :: 3
Requires-Python: >=3.8
Requires-Dist: beautifulsoup4
Requires-Dist: faker
Requires-Dist: loguru
Requires-Dist: lxml
Requires-Dist: pymongo
Requires-Dist: pymysql
Requires-Dist: redis
Requires-Dist: requests
Requires-Dist: telnetlib3
Requires-Dist: yagmail
